<?xml version="1.0" encoding="UTF-8"?>
<database defaultPhpNamingMethod="underscore" heavyIndexing="false" name="propel" package="plugins.sfPropelActAsTaggableBehaviorPlugin.lib.model" defaultIdMethod="native" noXsd="true"><table skipSql="false" abstract="false" name="tag" phpName="Tag" package="plugins.sfPropelActAsTaggableBehaviorPlugin.lib.model"><column autoIncrement="false" lazyLoad="false" name="id" phpName="ID" type="integer" required="true" primaryKey="true" autoincrement="true"/><column primaryKey="false" required="false" autoIncrement="false" lazyLoad="false" name="name" type="varchar" size="100"/><column primaryKey="false" required="false" autoIncrement="false" lazyLoad="false" name="is_triple" type="boolean" size="1"/><column primaryKey="false" required="false" autoIncrement="false" lazyLoad="false" name="triple_namespace" type="varchar" size="100"/><column primaryKey="false" required="false" autoIncrement="false" lazyLoad="false" name="triple_key" type="varchar" size="100"/><column primaryKey="false" required="false" autoIncrement="false" lazyLoad="false" name="triple_value" type="varchar" size="100"/><index name="name"><index-column name="name"/></index><index name="triple1"><index-column name="triple_namespace"/></index><index name="triple2"><index-column name="triple_key"/></index><index name="triple3"><index-column name="triple_value"/></index></table><table skipSql="false" abstract="false" name="tagging" phpName="Tagging" package="plugins.sfPropelActAsTaggableBehaviorPlugin.lib.model"><column autoIncrement="false" lazyLoad="false" name="id" phpName="ID" type="integer" required="true" primaryKey="true" autoincrement="true"/><column primaryKey="false" required="false" autoIncrement="false" lazyLoad="false" name="tag_id" type="varchar" size="100"/><column primaryKey="false" required="false" autoIncrement="false" lazyLoad="false" name="taggable_model" type="varchar" size="30"/><column primaryKey="false" required="false" autoIncrement="false" lazyLoad="false" name="taggable_id" type="integer"/><index name="tag"><index-column name="tag_id"/></index><index name="taggable"><index-column name="taggable_model"/><index-column name="taggable_id"/></index></table></database>
